{
    "schema_version":  1,
    "id":  "windowing.window-chrome",
    "display_name":  "WindowChrome",
    "kind":  "control",
    "status":  "in-progress",
    "maturity":  "lab",
    "priority":  "P1",
    "package":  "WinUI3.Senior.Windowing",
    "namespace":  "WinUI3.Senior.Windowing",
    "gallery_route":  "/windowing/window-chrome",
    "source_language":  "zh-CN",
    "owned_paths":  [
                        "catalog/Windowing/WindowChrome",
                        "src/WinUI3.Senior.Windowing/WindowChrome.cs",
                        "src/WinUI3.Senior.Windowing/WindowingContracts.cs",
                        "src/WinUI3.Senior.Windowing/WindowPlacementCoordinator.cs"
                    ],
    "depends_on":  [
                       "contracts.windowing"
                   ],
    "provides":  [
                     "control:windowing.window-chrome",
                     "WinUI3.Senior.Windowing.WindowPlacementCoordinator"
                 ],
    "archaeology_refs":  [

                         ],
    "license_review":  "not-required"
}
